MANIFEST.in
MIT-LICENSE.txt
README.rst
setup.py
doc_versions.egg-info/PKG-INFO
doc_versions.egg-info/SOURCES.txt
doc_versions.egg-info/dependency_links.txt
doc_versions.egg-info/top_level.txt
documents/__init__.py
documents/admin.py
documents/fields.py
documents/models.py
documents/retrospection.py
documents/tests.py
documents/utils.py
documents/management/__init__.py
documents/management/commands/__init__.py
documents/management/commands/documentscheck.py
documents/management/commands/drop_retrospection_data.py
documents/management/commands/fixdocuments_document_end.py
documents/management/commands/fixdocuments_overlapping.py
documents/management/commands/fixdocuments_remove_phantoms.py