Metadata-Version: 1.0
Name: doc-versions
Version: 0.1.1
Summary: Django app for tracking changes in models
Home-page: https://github.com/chtd/doc-versions
Author: CHTD
Author-email: info@chtd.ru
License: MIT
Platform: UNKNOWN
